odoo10_addon_hr_holidays_leave_auto_approve-10.0.1.0.1-py2.7-nspkg.pth
odoo/addons/hr_holidays_leave_auto_approve/README.rst
odoo/addons/hr_holidays_leave_auto_approve/__init__.py
odoo/addons/hr_holidays_leave_auto_approve/__manifest__.py
odoo/addons/hr_holidays_leave_auto_approve/i18n/ar.po
odoo/addons/hr_holidays_leave_auto_approve/i18n/cs_CZ.po
odoo/addons/hr_holidays_leave_auto_approve/i18n/de.po
odoo/addons/hr_holidays_leave_auto_approve/i18n/es.po
odoo/addons/hr_holidays_leave_auto_approve/i18n/fr.po
odoo/addons/hr_holidays_leave_auto_approve/i18n/hr.po
odoo/addons/hr_holidays_leave_auto_approve/i18n/hr_HR.po
odoo/addons/hr_holidays_leave_auto_approve/i18n/hr_holidays_leave_auto_approve.pot
odoo/addons/hr_holidays_leave_auto_approve/i18n/nl_NL.po
odoo/addons/hr_holidays_leave_auto_approve/i18n/sl.po
odoo/addons/hr_holidays_leave_auto_approve/models/__init__.py
odoo/addons/hr_holidays_leave_auto_approve/models/hr_holidays.py
odoo/addons/hr_holidays_leave_auto_approve/models/hr_holidays_status.py
odoo/addons/hr_holidays_leave_auto_approve/tests/__init__.py
odoo/addons/hr_holidays_leave_auto_approve/tests/test_hr_holidays_leave_auto_approve.py
odoo/addons/hr_holidays_leave_auto_approve/views/hr_holidays_status.xml
odoo10_addon_hr_holidays_leave_auto_approve-10.0.1.0.1.dist-info/METADATA
odoo10_addon_hr_holidays_leave_auto_approve-10.0.1.0.1.dist-info/RECORD
odoo10_addon_hr_holidays_leave_auto_approve-10.0.1.0.1.dist-info/WHEEL
odoo10_addon_hr_holidays_leave_auto_approve-10.0.1.0.1.dist-info/namespace_packages.txt
odoo10_addon_hr_holidays_leave_auto_approve-10.0.1.0.1.dist-info/top_level.txt
